loter/toolsfunc.py
loter/find_lib.py
loter/graph.py
loter/estimateh.py
loter/estimatea.py
loter/wrapper_cpp.py
loter/__init__.py
loter/errorhandler.py
loter/_loter_wrap.cpython-310-x86_64-linux-gnu.so
loter/metrics.py
loter/predcombine.py
loter/initparam.py
loter/utils.py
loter/initdata.py
loter/tree.py
loter/pipeline.py
loter/cli.py
loter/opti.py
loter/datastruct/parameter.py
loter/datastruct/__init__.py
loter/locanc/local_ancestry.py
loter/locanc/__init__.py
tests/test_estimateh.py
tests/__init__.py
tests/test_estimates.py
tests/test_estimatea.py
tests/generate_input.py
loter.libs/liblapack-029dbe9a.so.3.2.1
loter.libs/libgomp-f7e03b3e.so.1.0.0
loter.libs/libblas-8d819fb1.so.3.2.1
loter.libs/libgfortran-139be63a.so.3.0.0
loter-1.0.dist-info/METADATA
loter-1.0.dist-info/top_level.txt
loter-1.0.dist-info/entry_points.txt
loter-1.0.dist-info/WHEEL
loter-1.0.dist-info/LICENSE.txt
loter-1.0.dist-info/RECORD
